extras/__init__.py
extras/divide.py
extras/multiply.py
extras/power.py
a_simple_module-0.0.0.dist-info/METADATA
a_simple_module-0.0.0.dist-info/WHEEL
a_simple_module-0.0.0.dist-info/top_level.txt
a_simple_module-0.0.0.dist-info/RECORD
