Metadata-Version: 2.1
Name: a-simple-module
Version: 0.0.0
Summary: my first python package
Home-page: UNKNOWN
Author: Stijn Dom
Author-email: stijn.dom@hotmail.be
License: UNKNOWN
Keywords: python,first package,math
Platform: UNKNOWN
Classifier: Development Status :: 3 - Alpha
Classifier: Intended Audience :: Education
Classifier: Programming Language :: Python :: 3
Classifier: Operating System :: MacOS :: MacOS X
Classifier: Operating System :: Microsoft :: Windows
